README.md
setup.py
thanks/tx_listener.py
witness_thanks.egg-info/PKG-INFO
witness_thanks.egg-info/SOURCES.txt
witness_thanks.egg-info/dependency_links.txt
witness_thanks.egg-info/entry_points.txt
witness_thanks.egg-info/requires.txt
witness_thanks.egg-info/top_level.txt