Metadata-Version: 1.0
Name: witness-thanks
Version: 0.0.1
Summary: A thanks bot for STEEM witnesses to thank their voters after their vote
Home-page: http://github.com/emre/thanks
Author: emre yilmaz
Author-email: mail@emreyilmaz.me
License: MIT
Platform: UNKNOWN
